configstore/__init__.py
configstore/configstore.py
configstore/configstore_ctrl.py
goatconfigstore-2024.7.16.1622.dist-info/METADATA
goatconfigstore-2024.7.16.1622.dist-info/WHEEL
goatconfigstore-2024.7.16.1622.dist-info/entry_points.txt
goatconfigstore-2024.7.16.1622.dist-info/top_level.txt
goatconfigstore-2024.7.16.1622.dist-info/RECORD
