Metadata-Version: 2.1
Name: goatconfigstore
Version: 2024.7.16.1622
Summary: configtools - manage settings for your Python application with encrypted json files
Author-email: Chris Stacks <centerupt@gmail.com>
Classifier: Programming Language :: Python :: 3
Classifier: Operating System :: OS Independent
Requires-Python: >=3.7
Requires-Dist: click >=8.0.4
